[{"date": "2023-04-07", "meeting": [{"meeting_name": "衆議院 環境委員会", "remarks": [{"url": "https://kokkai.ndl.go.jp/txt/121104006X00420230407/77", "sentence": ["○漆間委員日本維新の会の漆間と申します。今法案の事前説明に当たり、カナダでの大熱波、二〇二一年に六百十九人の死者をもたらした事例を御説明いた…", "…者をもたらした事例を御説明いただきましたが、今回、今法案に当たって、カナダの教訓がどのように生かされているのか、法律化の意義についてまずお伺…"]}, {"url": "https://kokkai.ndl.go.jp/txt/121104006X00420230407/79", "sentence": ["○漆間委員カナダのほかにでも、ヨーロッパだとかでは、数千人規模で、昨年の夏、死者が出ているようなところでありまして、これは熱波で起こったとい…"]}, {"url": "https://kokkai.ndl.go.jp/txt/121104006X00420230407/81", "sentence": ["○漆間委員カナダもヨーロッパも、これまでは起こり得ないだろうと思っていたところでこういう極端な気候が起こったということで、これから可能性もあ…", "…を飛ばしまして、今法案の事前説明に当たりましては、神ノ田部長様より、カナダの教訓として、民間団体連携がすごく重要だということをお話でいただき…"]}, {"url": "https://kokkai.ndl.go.jp/txt/121104006X00420230407/83", "sentence": []}, {"url": "https://kokkai.ndl.go.jp/txt/121104006X00420230407/85", "sentence": []}, {"url": "https://kokkai.ndl.go.jp/txt/121104006X00420230407/87", "sentence": []}, {"url": "https://kokkai.ndl.go.jp/txt/121104006X00420230407/90", "sentence": []}, {"url": "https://kokkai.ndl.go.jp/txt/121104006X00420230407/92", "sentence": []}, {"url": "https://kokkai.ndl.go.jp/txt/121104006X00420230407/94", "sentence": []}, {"url": "https://kokkai.ndl.go.jp/txt/121104006X00420230407/96", "sentence": []}, {"url": "https://kokkai.ndl.go.jp/txt/121104006X00420230407/98", "sentence": []}, {"url": "https://kokkai.ndl.go.jp/txt/121104006X00420230407/100", "sentence": []}]}]}]