[{"date": "2022-03-09", "meeting": [{"meeting_name": "衆議院 経済産業委員会", "remarks": [{"url": "https://kokkai.ndl.go.jp/txt/120804080X00320220309/46", "sentence": []}, {"url": "https://kokkai.ndl.go.jp/txt/120804080X00320220309/48", "sentence": []}, {"url": "https://kokkai.ndl.go.jp/txt/120804080X00320220309/50", "sentence": ["…携などできればと思いますので、よろしくお願いいたします。続きまして、各国の万博参加の流れにつきましては、まず、日本国が世界百九十三か国を招請…"]}, {"url": "https://kokkai.ndl.go.jp/txt/120804080X00320220309/52", "sentence": []}, {"url": "https://kokkai.ndl.go.jp/txt/120804080X00320220309/54", "sentence": []}, {"url": "https://kokkai.ndl.go.jp/txt/120804080X00320220309/56", "sentence": []}, {"url": "https://kokkai.ndl.go.jp/txt/120804080X00320220309/58", "sentence": []}, {"url": "https://kokkai.ndl.go.jp/txt/120804080X00320220309/60", "sentence": []}, {"url": "https://kokkai.ndl.go.jp/txt/120804080X00320220309/62", "sentence": []}, {"url": "https://kokkai.ndl.go.jp/txt/120804080X00320220309/64", "sentence": []}, {"url": "https://kokkai.ndl.go.jp/txt/120804080X00320220309/66", "sentence": []}, {"url": "https://kokkai.ndl.go.jp/txt/120804080X00320220309/68", "sentence": []}]}]}, {"date": "2022-11-02", "meeting": [{"meeting_name": "衆議院 法務委員会", "remarks": [{"url": "https://kokkai.ndl.go.jp/txt/121005206X00420221102/108", "sentence": []}, {"url": "https://kokkai.ndl.go.jp/txt/121005206X00420221102/110", "sentence": []}, {"url": "https://kokkai.ndl.go.jp/txt/121005206X00420221102/112", "sentence": []}, {"url": "https://kokkai.ndl.go.jp/txt/121005206X00420221102/115", "sentence": []}, {"url": "https://kokkai.ndl.go.jp/txt/121005206X00420221102/117", "sentence": []}, {"url": "https://kokkai.ndl.go.jp/txt/121005206X00420221102/119", "sentence": ["○漆間委員国際捜査の共助という仕組みがあって、これは多国間でも、各国の法の違いを乗り越えて捜査協力をする枠組みがあるということで御答弁をいた…"]}, {"url": "https://kokkai.ndl.go.jp/txt/121005206X00420221102/121", "sentence": []}]}]}, {"date": "2023-04-14", "meeting": [{"meeting_name": "衆議院 法務委員会", "remarks": [{"url": "https://kokkai.ndl.go.jp/txt/121105206X00920230414/126", "sentence": []}, {"url": "https://kokkai.ndl.go.jp/txt/121105206X00920230414/128", "sentence": []}, {"url": "https://kokkai.ndl.go.jp/txt/121105206X00920230414/130", "sentence": ["…、開催を二年後に控えた二〇二五年大阪・関西万博でありますが、万博では各国の要人が集まりまして、世界における日本のプレゼンス向上を目指した様々…"]}, {"url": "https://kokkai.ndl.go.jp/txt/121105206X00920230414/132", "sentence": []}, {"url": "https://kokkai.ndl.go.jp/txt/121105206X00920230414/134", "sentence": []}, {"url": "https://kokkai.ndl.go.jp/txt/121105206X00920230414/136", "sentence": []}, {"url": "https://kokkai.ndl.go.jp/txt/121105206X00920230414/138", "sentence": ["…姻制度の緩和についてお伺いしたいと思います。少子化対策で、ヨーロッパ各国の比較の議論として、同じだけの財政的子育て支援をしていても、それが効…"]}, {"url": "https://kokkai.ndl.go.jp/txt/121105206X00920230414/140", "sentence": []}]}]}, {"date": "2023-04-25", "meeting": [{"meeting_name": "衆議院 法務委員会", "remarks": [{"url": "https://kokkai.ndl.go.jp/txt/121105206X01320230425/172", "sentence": []}, {"url": "https://kokkai.ndl.go.jp/txt/121105206X01320230425/174", "sentence": []}, {"url": "https://kokkai.ndl.go.jp/txt/121105206X01320230425/176", "sentence": []}, {"url": "https://kokkai.ndl.go.jp/txt/121105206X01320230425/178", "sentence": []}, {"url": "https://kokkai.ndl.go.jp/txt/121105206X01320230425/180", "sentence": []}, {"url": "https://kokkai.ndl.go.jp/txt/121105206X01320230425/182", "sentence": []}, {"url": "https://kokkai.ndl.go.jp/txt/121105206X01320230425/184", "sentence": []}, {"url": "https://kokkai.ndl.go.jp/txt/121105206X01320230425/186", "sentence": []}, {"url": "https://kokkai.ndl.go.jp/txt/121105206X01320230425/188", "sentence": []}, {"url": "https://kokkai.ndl.go.jp/txt/121105206X01320230425/190", "sentence": []}, {"url": "https://kokkai.ndl.go.jp/txt/121105206X01320230425/192", "sentence": []}, {"url": "https://kokkai.ndl.go.jp/txt/121105206X01320230425/194", "sentence": []}, {"url": "https://kokkai.ndl.go.jp/txt/121105206X01320230425/196", "sentence": ["…フールマン原則、このバランスのお話だと主に思っております。これは、今各国でもいろいろ模索されているところであります。まさにこういったことを、…", "…いろいろ模索されているところであります。まさにこういったことを、世界各国の人々が集まる、世界から最も注目を浴びる機会であります二〇二五年の大…"]}, {"url": "https://kokkai.ndl.go.jp/txt/121105206X01320230425/198", "sentence": []}]}]}, {"date": "2023-05-10", "meeting": [{"meeting_name": "衆議院 法務委員会", "remarks": [{"url": "https://kokkai.ndl.go.jp/txt/121105206X01520230510/129", "sentence": ["…の協力の枠組みについてお伺いしたところでございます。答弁としまして、各国間の相互主義の下での捜査共助、二国間、多国間における刑事共助条約によ…"]}, {"url": "https://kokkai.ndl.go.jp/txt/121105206X01520230510/131", "sentence": []}, {"url": "https://kokkai.ndl.go.jp/txt/121105206X01520230510/133", "sentence": []}, {"url": "https://kokkai.ndl.go.jp/txt/121105206X01520230510/135", "sentence": []}, {"url": "https://kokkai.ndl.go.jp/txt/121105206X01520230510/137", "sentence": []}, {"url": "https://kokkai.ndl.go.jp/txt/121105206X01520230510/139", "sentence": []}, {"url": "https://kokkai.ndl.go.jp/txt/121105206X01520230510/141", "sentence": []}, {"url": "https://kokkai.ndl.go.jp/txt/121105206X01520230510/143", "sentence": []}, {"url": "https://kokkai.ndl.go.jp/txt/121105206X01520230510/145", "sentence": []}]}]}]