[{"date": "2022-03-11", "meeting": [{"meeting_name": "衆議院 内閣委員会", "remarks": [{"url": "https://kokkai.ndl.go.jp/txt/120804889X00820220311/46", "sentence": []}, {"url": "https://kokkai.ndl.go.jp/txt/120804889X00820220311/48", "sentence": []}, {"url": "https://kokkai.ndl.go.jp/txt/120804889X00820220311/50", "sentence": ["…られたわけであります。この写真を御覧になっていただいて分かるとおり、海岸に白く写っているもの、赤かったり青かったりするもの、これは全部ごみで…", "…であります。このように、尖閣周辺の調査に行かれた方々からは、魚釣島の海岸におびただしい数の漂着ごみがあるということが報告をされました。魚釣島…"]}, {"url": "https://kokkai.ndl.go.jp/txt/120804889X00820220311/52", "sentence": ["…というふうに聞いております。これは、二月の末にウクライナの国防大臣から岸防衛大臣に対して御依頼があって、そして防弾チョッキ、ヘルメットを自衛…"]}, {"url": "https://kokkai.ndl.go.jp/txt/120804889X00820220311/54", "sentence": []}, {"url": "https://kokkai.ndl.go.jp/txt/120804889X00820220311/56", "sentence": []}, {"url": "https://kokkai.ndl.go.jp/txt/120804889X00820220311/58", "sentence": []}, {"url": "https://kokkai.ndl.go.jp/txt/120804889X00820220311/60", "sentence": []}, {"url": "https://kokkai.ndl.go.jp/txt/120804889X00820220311/62", "sentence": []}, {"url": "https://kokkai.ndl.go.jp/txt/120804889X00820220311/64", "sentence": []}]}]}]