[{"date": "2022-02-17", "meeting": [{"meeting_name": "衆議院 予算委員会第七分科会", "remarks": [{"url": "https://kokkai.ndl.go.jp/txt/120805271X00220220217/60", "sentence": []}, {"url": "https://kokkai.ndl.go.jp/txt/120805271X00220220217/62", "sentence": []}, {"url": "https://kokkai.ndl.go.jp/txt/120805271X00220220217/64", "sentence": []}, {"url": "https://kokkai.ndl.go.jp/txt/120805271X00220220217/66", "sentence": []}, {"url": "https://kokkai.ndl.go.jp/txt/120805271X00220220217/68", "sentence": ["…している既存のガソリンスタンド、ＳＳ、サービスステーション、これは、社会的インフラとしても存在し、今後、水素ステーションとして充填器や、電動…"]}, {"url": "https://kokkai.ndl.go.jp/txt/120805271X00220220217/70", "sentence": ["…か、車が先かという問題もありまして、いろいろなことで、むしろ積極的に社会の考え方、そして、社会に必要とされているものだよということを、やはり…", "…もありまして、いろいろなことで、むしろ積極的に社会の考え方、そして、社会に必要とされているものだよということを、やはりサービスステーション、…"]}, {"url": "https://kokkai.ndl.go.jp/txt/120805271X00220220217/72", "sentence": []}]}]}, {"date": "2022-10-26", "meeting": [{"meeting_name": "衆議院 経済産業委員会", "remarks": [{"url": "https://kokkai.ndl.go.jp/txt/121004080X00220221026/16", "sentence": ["…生に向けた取組が必要になると考えてはおりますが、さらに、コロナ禍では社会や人々のライフスタイルが大きく変化したことも踏まえ、中小企業において…"]}, {"url": "https://kokkai.ndl.go.jp/txt/121004080X00220221026/18", "sentence": []}, {"url": "https://kokkai.ndl.go.jp/txt/121004080X00220221026/20", "sentence": []}, {"url": "https://kokkai.ndl.go.jp/txt/121004080X00220221026/22", "sentence": []}, {"url": "https://kokkai.ndl.go.jp/txt/121004080X00220221026/24", "sentence": ["…まとめられました。また、先日の西村大臣の所信挨拶において、「炭素中立社会の実現に向け、日本の経済社会、産業構造のグリーントランスフォーメーシ…", "…の西村大臣の所信挨拶において、「炭素中立社会の実現に向け、日本の経済社会、産業構造のグリーントランスフォーメーション、ＧＸを進めます。」と発…", "…Ｘについては、現在、政府のＧＸ実行会議において、脱炭素化のための経済社会、産業構造の変革へ向けた検討が行われております。その中でも、燃焼時に…"]}, {"url": "https://kokkai.ndl.go.jp/txt/121004080X00220221026/26", "sentence": []}]}]}, {"date": "2023-02-20", "meeting": [{"meeting_name": "衆議院 予算委員会第三分科会", "remarks": [{"url": "https://kokkai.ndl.go.jp/txt/121105268X00120230220/47", "sentence": ["…の後退に歯止めをかけるとともに、あわせて今後我が国が目指すべき低炭素社会の実現につながる措置を講ずる観点から、平成二十一年度税制改正において…"]}, {"url": "https://kokkai.ndl.go.jp/txt/121105268X00120230220/49", "sentence": []}, {"url": "https://kokkai.ndl.go.jp/txt/121105268X00120230220/51", "sentence": []}, {"url": "https://kokkai.ndl.go.jp/txt/121105268X00120230220/53", "sentence": []}, {"url": "https://kokkai.ndl.go.jp/txt/121105268X00120230220/55", "sentence": []}, {"url": "https://kokkai.ndl.go.jp/txt/121105268X00120230220/57", "sentence": ["…タル化の急速な進展やサプライチェーンの見直しの動きなど、内外の経済、社会の構造変化を受けて大きく大きく変化しております。新型コロナウイルス感…", "…、税関を取り巻く環境変化に的確に対応し、税関の使命である安全、安心な社会の実現、適正かつ公平な関税などの賦課徴収、貿易円滑化の推進を着実に果…"]}, {"url": "https://kokkai.ndl.go.jp/txt/121105268X00120230220/59", "sentence": []}]}, {"meeting_name": "衆議院 予算委員会第七分科会", "remarks": [{"url": "https://kokkai.ndl.go.jp/txt/121105271X00120230220/112", "sentence": ["…し、商用化を見越したサプライチェーンでなければなりません。需要側には社会実装のための試験や研究も必要であり、重要となってまいります。それを促…"]}, {"url": "https://kokkai.ndl.go.jp/txt/121105271X00120230220/114", "sentence": []}, {"url": "https://kokkai.ndl.go.jp/txt/121105271X00120230220/116", "sentence": []}, {"url": "https://kokkai.ndl.go.jp/txt/121105271X00120230220/118", "sentence": []}, {"url": "https://kokkai.ndl.go.jp/txt/121105271X00120230220/120", "sentence": []}, {"url": "https://kokkai.ndl.go.jp/txt/121105271X00120230220/122", "sentence": []}, {"url": "https://kokkai.ndl.go.jp/txt/121105271X00120230220/124", "sentence": []}, {"url": "https://kokkai.ndl.go.jp/txt/121105271X00120230220/126", "sentence": []}, {"url": "https://kokkai.ndl.go.jp/txt/121105271X00120230220/128", "sentence": []}, {"url": "https://kokkai.ndl.go.jp/txt/121105271X00120230220/130", "sentence": []}, {"url": "https://kokkai.ndl.go.jp/txt/121105271X00120230220/132", "sentence": []}]}]}]