[{"date": "2023-05-31", "meeting": [{"meeting_name": "参議院 東日本大震災復興特別委員会", "remarks": [{"url": "https://kokkai.ndl.go.jp/txt/121114858X00620230531/7", "sentence": ["…ず、復興に関連する予算、財源についてお尋ねします。令和五年度税制改正大綱における防衛力強化に係る財源確保のための税制措置についてですが、前段…"]}, {"url": "https://kokkai.ndl.go.jp/txt/121114858X00620230531/9", "sentence": []}, {"url": "https://kokkai.ndl.go.jp/txt/121114858X00620230531/11", "sentence": []}, {"url": "https://kokkai.ndl.go.jp/txt/121114858X00620230531/13", "sentence": []}, {"url": "https://kokkai.ndl.go.jp/txt/121114858X00620230531/15", "sentence": []}, {"url": "https://kokkai.ndl.go.jp/txt/121114858X00620230531/17", "sentence": []}, {"url": "https://kokkai.ndl.go.jp/txt/121114858X00620230531/19", "sentence": []}, {"url": "https://kokkai.ndl.go.jp/txt/121114858X00620230531/21", "sentence": []}, {"url": "https://kokkai.ndl.go.jp/txt/121114858X00620230531/23", "sentence": []}, {"url": "https://kokkai.ndl.go.jp/txt/121114858X00620230531/25", "sentence": []}, {"url": "https://kokkai.ndl.go.jp/txt/121114858X00620230531/28", "sentence": []}]}]}]