[{"date": "2023-05-30", "meeting": [{"meeting_name": "参議院 国土交通委員会", "remarks": [{"url": "https://kokkai.ndl.go.jp/txt/121114319X01620230530/22", "sentence": ["…済機構法の一部を改正する法律案について質問いたします。まず、高速道路の料金徴収期間の延長について伺います。本法律案では、高速道路の更新、進化…", "…いて伺います。本法律案では、高速道路の更新、進化の財源を確保するため、料金徴収期限を令和九十七年まで五十年延長した上で、それまでの間、債務返…", "…う、こういった仕組みでございます。そして、本法律案においても、従来の有料道路制度と同様に、債務完済後にはこの高速道路を無料開放し、料金を徴収…", "…においても、従来の有料道路制度と同様に、債務完済後にはこの高速道路を無料開放し、料金を徴収しない仕組みだと、このように説明をしています。また…", "…、従来の有料道路制度と同様に、債務完済後にはこの高速道路を無料開放し、料金を徴収しない仕組みだと、このように説明をしています。また、私もそう…", "…した。六十年余りがたつわけでありますけれども、これまでも、幾度もこの無料開放という約束が先送りされてきました。この説明をいつまで続けるのか、…", "…るを得ません。法律上は令和九十七年ですから、二一一五年の九月三十日まで料金徴収を終える仕組みであります。法律上の立て付けはさておいて、大臣は…", "…て付けはさておいて、大臣は、この今回の令和九十七年、二一一五年までに、料金徴収期限までにこの料金の徴収を終了して高速道路が無料に開放される日…", "…臣は、この今回の令和九十七年、二一一五年までに、料金徴収期限までにこの料金の徴収を終了して高速道路が無料に開放される日が来ると本当にお考えな…", "…一一五年までに、料金徴収期限までにこの料金の徴収を終了して高速道路が無料に開放される日が来ると本当にお考えなのかどうなのか、大臣の率直な御意…"]}, {"url": "https://kokkai.ndl.go.jp/txt/121114319X01620230530/24", "sentence": ["…の参考人の方からもいろいろ貴重な御意見を伺いました。その中で、完全に無料になる、無料開放されるというこの説明については少し無理があると、こう…", "…からもいろいろ貴重な御意見を伺いました。その中で、完全に無料になる、無料開放されるというこの説明については少し無理があると、こういった、これ…", "…なった令和三年八月の国土幹線道路部会の中間答申でも、将来、高速道路は無料になるという説明に対する不信感が高まっていると、こんなふうに指摘をさ…", "…、こんなふうに指摘をされています。やはり、この債務完済後に高速道路を無料開放するという説明を続けるのにはいささか無理が来ているのかなと、こん…", "…ません、世論調査では、現在、高速道路の建設、維持修繕、更新の費用は通行料金で賄っているが、二〇六五年以降は無料になり、維持修繕、更新の費用は…", "…建設、維持修繕、更新の費用は通行料金で賄っているが、二〇六五年以降は無料になり、維持修繕、更新の費用は税金で賄う制度になっている、一方で、こ…", "…、一方で、この維持修繕、更新の費用は引き続き高速道路を利用する人が通行料金により負担すべきとの考えもある、高速道路の維持修繕、更新の費用の在…", "…のが五・五％、税金で賄っていくべきだと思うが、ある程度は高速道路の通行料金で賄うこともやむを得ない、こういった御意見が三〇・四％、高速道路の…", "…で賄うこともやむを得ない、こういった御意見が三〇・四％、高速道路の通行料金で賄っていくべきだと思うけれども、ある程度は税金で賄うこともやむを…", "…うこともやむを得ないと、これは四四・五％でした。そして、税金でなく高速料金の通行料で賄っていくべきが一八・四％と。こういう結果だったわけであ…", "…むを得ないと、これは四四・五％でした。そして、税金でなく高速料金の通行料で賄っていくべきが一八・四％と。こういう結果だったわけでありますけれ…", "…も。この結果には様々な見解があると思いますが、しかし、少なくとも、この料金徴収期限までに高速道路が無料開放され、通行料金の負担はなくなるもの…", "…ると思いますが、しかし、少なくとも、この料金徴収期限までに高速道路が無料開放され、通行料金の負担はなくなるものと国民が信じて疑わないというよ…", "…しかし、少なくとも、この料金徴収期限までに高速道路が無料開放され、通行料金の負担はなくなるものと国民が信じて疑わないというような状況ではどう…", "…いというような状況ではどう見てもないというふうに思いますし、全額を通行料金で賄う今の仕組みについても、ある程度の公費投入によって負担が分散さ…"]}, {"url": "https://kokkai.ndl.go.jp/txt/121114319X01620230530/26", "sentence": ["…のかなというふうに思っています。そういったことも踏まえて、次に、この有料道路制度の抜本的な見直しについて少し伺いたいと思います。局長からも必…", "…ら、そのことも踏まえて質問させてください。この償還主義を始め、現行の有料道路制度の基本的な考え方というのは、先ほどありました六十年以上前の高…", "…みを考えなければならないと、こういうふうに思っています。例えば、永久有料化、道路の無料公開の原則の見直しなども含めて模索をしていってほしいと…", "…ばならないと、こういうふうに思っています。例えば、永久有料化、道路の無料公開の原則の見直しなども含めて模索をしていってほしいと、こういうふう…", "…是非大臣、このことを私は約束してもらいたいと思うんです。二一一五年まで料金徴収ができたからいいんだではなくて、やはり今後の状況を的確に判断し…"]}, {"url": "https://kokkai.ndl.go.jp/txt/121114319X01620230530/28", "sentence": ["…ると、我が国のこの物流、人流には、自家用車よりも、やはり私は、この高速料金について、営自格差というか、まあ格差と言うと少し言葉が適切でないの…", "…くとも私は、今後二〇二四年問題などもありますから、営業用車両だけは基本料金を三割に引き下げるべきではないかと、こんなふうに思っています。高速…", "…金を三割に引き下げるべきではないかと、こんなふうに思っています。高速の料金の在り方いろいろ難しいと思いますけれども、この営業用車両に対する考…"]}, {"url": "https://kokkai.ndl.go.jp/txt/121114319X01620230530/30", "sentence": ["○森屋隆君やはり高速料金が、営業車ですから、そこを結果的に、その営業車を優遇するという言い方が適切ではないのかもしれませんけども、そのことが…", "…路において大規模な渋滞が発生しています。そのようなときには、当然、高速料金が有するこの特急料金的な意味合い、敏速に早く目的地に着くというよう…", "…滞が発生しています。そのようなときには、当然、高速料金が有するこの特急料金的な意味合い、敏速に早く目的地に着くというようなことが薄れてしまう…"]}, {"url": "https://kokkai.ndl.go.jp/txt/121114319X01620230530/32", "sentence": []}, {"url": "https://kokkai.ndl.go.jp/txt/121114319X01620230530/34", "sentence": ["…方などについて、基本的な考え方というのが示されていないと思っています。料金徴収期間が二一一五年という未来まで延長するというのであれば、私は、…", "…ていく中で共存をできるような状況をつくり上げていくのか、高速道路、今回料金を取っていくというような議案でありますけれども、それと含めて、営業…"]}, {"url": "https://kokkai.ndl.go.jp/txt/121114319X01620230530/36", "sentence": ["…源というのはどのように確保を考えているのか、仮にこれを高速道路利用者の料金負担に求めるということなのであれば、この費用対効果、実用性などの観…"]}, {"url": "https://kokkai.ndl.go.jp/txt/121114319X01620230530/38", "sentence": []}, {"url": "https://kokkai.ndl.go.jp/txt/121114319X01620230530/192", "sentence": ["…維持管理の重要性が増大する中、本法施行後五年以内を目途として、利用者の料金負担の抑制と利便性の向上に貢献し、ライフサイクルコストを最小化する…", "…備特別措置法第二十三条第一項第一号から第三号までに掲げる高速道路に係る料金の基準等、高速道路資産の管理の在り方について検討を加え、その結果に…", "…講ずること。五今国会での議論において言及された定額制度を始め、あらゆる料金体系を地方創生や国民生活と経済発展に資する観点から勘案した上で、利…", "…現するために必要となる費用負担の在り方について早急に検討し、高速道路の料金制度について、永久に有料にするのか、無料にするのかの議論を進め、可…", "…負担の在り方について早急に検討し、高速道路の料金制度について、永久に有料にするのか、無料にするのかの議論を進め、可及的速やかに結論を出すこと…", "…いて早急に検討し、高速道路の料金制度について、永久に有料にするのか、無料にするのかの議論を進め、可及的速やかに結論を出すこと。六高速道路の維…", "…将来調達金利の見通しと将来交通量の推計の設定が債務返済の財源である貸付料の推計に直結するものであり、その実績値が示されることは償還計画の妥当…"]}]}]}]