[{"date": "2023-10-27", "meeting": [{"meeting_name": "衆議院 予算委員会", "remarks": [{"url": "https://kokkai.ndl.go.jp/txt/121205261X00220231027/4", "sentence": []}, {"url": "https://kokkai.ndl.go.jp/txt/121205261X00220231027/6", "sentence": []}, {"url": "https://kokkai.ndl.go.jp/txt/121205261X00220231027/8", "sentence": []}, {"url": "https://kokkai.ndl.go.jp/txt/121205261X00220231027/10", "sentence": []}, {"url": "https://kokkai.ndl.go.jp/txt/121205261X00220231027/12", "sentence": []}, {"url": "https://kokkai.ndl.go.jp/txt/121205261X00220231027/15", "sentence": ["○萩生田委員今後のＮＴＴ法の在り方についてお尋ねをします。日本電信電話株式会社等に関する法律、いわゆるＮＴＴ法の在り方について、自民党政調会…", "…についてお尋ねをします。日本電信電話株式会社等に関する法律、いわゆるＮＴＴ法の在り方について、自民党政調会の中に私自身が責任者となるプロジェ…", "…ことはありません。外資に買われるんじゃないか。いやいや、国の株は直接ＮＴＴに売れば外資が介入する余地はないわけですから、そういう心配は全くな…", "…てきました。こういう人たちと公平公正な競争環境をしっかり残しながら、ＮＴＴとして今不具合があるとすれば、例えば、研究成果の公表、普及、これは…", "…ます。また、この売却益は、当初は防衛費を前提に考えたんですけれども、ＮＴＴの株ですから、やはり我が国の情報通信の研究開発に使うべきだという部…", "…ります。そこで、間もなく党としても提言を取りまとめて、提言を踏まえてＮＴＴ法のあるべき姿について政府内で議論を加速していただきたいと思ってい…", "…ていただきたいと思っています。改めて、私どもが取組をしておりますこのＮＴＴ法の改正、見直し、総理のリーダーシップで、世界に打ちかつ情報通信産…"]}, {"url": "https://kokkai.ndl.go.jp/txt/121205261X00220231027/17", "sentence": []}, {"url": "https://kokkai.ndl.go.jp/txt/121205261X00220231027/19", "sentence": []}, {"url": "https://kokkai.ndl.go.jp/txt/121205261X00220231027/21", "sentence": []}, {"url": "https://kokkai.ndl.go.jp/txt/121205261X00220231027/23", "sentence": []}]}]}]