[{"date": "2022-04-25", "meeting": [{"meeting_name": "参議院 決算委員会", "remarks": [{"url": "https://kokkai.ndl.go.jp/txt/120814103X00620220425/30", "sentence": []}, {"url": "https://kokkai.ndl.go.jp/txt/120814103X00620220425/32", "sentence": []}, {"url": "https://kokkai.ndl.go.jp/txt/120814103X00620220425/34", "sentence": []}, {"url": "https://kokkai.ndl.go.jp/txt/120814103X00620220425/36", "sentence": []}, {"url": "https://kokkai.ndl.go.jp/txt/120814103X00620220425/38", "sentence": []}, {"url": "https://kokkai.ndl.go.jp/txt/120814103X00620220425/40", "sentence": []}, {"url": "https://kokkai.ndl.go.jp/txt/120814103X00620220425/42", "sentence": []}, {"url": "https://kokkai.ndl.go.jp/txt/120814103X00620220425/44", "sentence": ["…期間というものを空けずに接種券が届いてしまったために、それをもらった住民は慌てて医療機関に行って三回目の接種をしてくださいというふうに言った…"]}, {"url": "https://kokkai.ndl.go.jp/txt/120814103X00620220425/46", "sentence": []}]}]}, {"date": "2022-05-16", "meeting": [{"meeting_name": "参議院 決算委員会", "remarks": [{"url": "https://kokkai.ndl.go.jp/txt/120814103X00820220516/10", "sentence": []}, {"url": "https://kokkai.ndl.go.jp/txt/120814103X00820220516/12", "sentence": ["…ているという状況でございますけれども、これ各地域で接種券を接種者に、住民にお配りをしているというところで、実はこの期間が、二回目から三回目、…", "…なっているわけでございますけれども、六か月たたないうちにその接種券が住民の元へ届いたということで、御本人もどのくらいの間隔が空けたかもう分か…"]}, {"url": "https://kokkai.ndl.go.jp/txt/120814103X00820220516/14", "sentence": ["…するという話もありまして、順次変わってきておりますのでいろいろな点で住民にも理解がなかなか進んでいない面もありますので、そういった点を是非御…"]}]}]}]