[{"date": "2022-02-16", "meeting": [{"meeting_name": "衆議院 予算委員会第六分科会", "remarks": [{"url": "https://kokkai.ndl.go.jp/txt/120805274X00120220216/228", "sentence": []}, {"url": "https://kokkai.ndl.go.jp/txt/120805274X00120220216/230", "sentence": ["…した声は、今回の見直しの内容あるいはその趣旨についてこれから生産者に周知していくという中で、まだそういった内容が周知されていないという中での…", "…についてこれから生産者に周知していくという中で、まだそういった内容が周知されていないという中での声ということはあると思いますが、一方で、例え…"]}, {"url": "https://kokkai.ndl.go.jp/txt/120805274X00120220216/232", "sentence": []}, {"url": "https://kokkai.ndl.go.jp/txt/120805274X00120220216/234", "sentence": []}, {"url": "https://kokkai.ndl.go.jp/txt/120805274X00120220216/236", "sentence": []}, {"url": "https://kokkai.ndl.go.jp/txt/120805274X00120220216/238", "sentence": []}, {"url": "https://kokkai.ndl.go.jp/txt/120805274X00120220216/240", "sentence": []}, {"url": "https://kokkai.ndl.go.jp/txt/120805274X00120220216/242", "sentence": []}, {"url": "https://kokkai.ndl.go.jp/txt/120805274X00120220216/244", "sentence": []}]}]}]