[{"date": "2022-11-04", "meeting": [{"meeting_name": "衆議院 厚生労働委員会", "remarks": [{"url": "https://kokkai.ndl.go.jp/txt/121004260X00620221104/168", "sentence": []}, {"url": "https://kokkai.ndl.go.jp/txt/121004260X00620221104/170", "sentence": []}, {"url": "https://kokkai.ndl.go.jp/txt/121004260X00620221104/172", "sentence": []}, {"url": "https://kokkai.ndl.go.jp/txt/121004260X00620221104/174", "sentence": ["…司令塔とならなければ、縦割り行政のままです。また、厚生労働省とただの連携になってしまえば、責任の所在も明確でなくなり、意思決定が遅れることに…", "…て、政府と自治体の意見の食い違いから不協和音が生じました。自治体との連携も重要である中、その点においても、今回の施策には課題があるのではない…", "…となって、今後を担う感染症の知識を持つ研究者の育成、つまりは大学との連携や、また研修などに取り組み、感染症と社会政策と両方の知識を兼ね備えた…"]}]}]}, {"date": "2023-03-15", "meeting": [{"meeting_name": "衆議院 厚生労働委員会", "remarks": [{"url": "https://kokkai.ndl.go.jp/txt/121104260X00320230315/162", "sentence": []}, {"url": "https://kokkai.ndl.go.jp/txt/121104260X00320230315/164", "sentence": []}, {"url": "https://kokkai.ndl.go.jp/txt/121104260X00320230315/166", "sentence": []}, {"url": "https://kokkai.ndl.go.jp/txt/121104260X00320230315/168", "sentence": []}, {"url": "https://kokkai.ndl.go.jp/txt/121104260X00320230315/170", "sentence": []}, {"url": "https://kokkai.ndl.go.jp/txt/121104260X00320230315/172", "sentence": []}, {"url": "https://kokkai.ndl.go.jp/txt/121104260X00320230315/174", "sentence": []}, {"url": "https://kokkai.ndl.go.jp/txt/121104260X00320230315/176", "sentence": []}, {"url": "https://kokkai.ndl.go.jp/txt/121104260X00320230315/178", "sentence": ["…働省が主体となって、主導的立場となって、年金機構と、そして自治体との連携、これが取れるように図っていただきたいと思います。やはり、今この時代…"]}]}]}, {"date": "2023-03-29", "meeting": [{"meeting_name": "衆議院 厚生労働委員会", "remarks": [{"url": "https://kokkai.ndl.go.jp/txt/121104260X00520230329/213", "sentence": []}, {"url": "https://kokkai.ndl.go.jp/txt/121104260X00520230329/215", "sentence": []}, {"url": "https://kokkai.ndl.go.jp/txt/121104260X00520230329/217", "sentence": []}, {"url": "https://kokkai.ndl.go.jp/txt/121104260X00520230329/219", "sentence": []}, {"url": "https://kokkai.ndl.go.jp/txt/121104260X00520230329/221", "sentence": ["○吉田（と）委員今、多職種の連携で円滑に進むような体制づくりを行っているという御説明をいただきましたが、現実として脳死移植が増えていない。研…"]}, {"url": "https://kokkai.ndl.go.jp/txt/121104260X00520230329/223", "sentence": []}, {"url": "https://kokkai.ndl.go.jp/txt/121104260X00520230329/225", "sentence": []}, {"url": "https://kokkai.ndl.go.jp/txt/121104260X00520230329/227", "sentence": []}, {"url": "https://kokkai.ndl.go.jp/txt/121104260X00520230329/229", "sentence": []}, {"url": "https://kokkai.ndl.go.jp/txt/121104260X00520230329/231", "sentence": []}, {"url": "https://kokkai.ndl.go.jp/txt/121104260X00520230329/233", "sentence": []}, {"url": "https://kokkai.ndl.go.jp/txt/121104260X00520230329/235", "sentence": []}, {"url": "https://kokkai.ndl.go.jp/txt/121104260X00520230329/237", "sentence": []}, {"url": "https://kokkai.ndl.go.jp/txt/121104260X00520230329/239", "sentence": []}, {"url": "https://kokkai.ndl.go.jp/txt/121104260X00520230329/241", "sentence": []}, {"url": "https://kokkai.ndl.go.jp/txt/121104260X00520230329/243", "sentence": []}]}]}, {"date": "2023-04-21", "meeting": [{"meeting_name": "衆議院 厚生労働委員会", "remarks": [{"url": "https://kokkai.ndl.go.jp/txt/121104260X01020230421/101", "sentence": []}, {"url": "https://kokkai.ndl.go.jp/txt/121104260X01020230421/103", "sentence": []}, {"url": "https://kokkai.ndl.go.jp/txt/121104260X01020230421/105", "sentence": []}, {"url": "https://kokkai.ndl.go.jp/txt/121104260X01020230421/107", "sentence": []}, {"url": "https://kokkai.ndl.go.jp/txt/121104260X01020230421/109", "sentence": ["…に、農林水産省の生産過程における取組支援も重要と考えますので、更なる連携をよろしくお願いいたします。では、続きまして、時間の関係上、八番の質…"]}, {"url": "https://kokkai.ndl.go.jp/txt/121104260X01020230421/111", "sentence": []}, {"url": "https://kokkai.ndl.go.jp/txt/121104260X01020230421/113", "sentence": []}, {"url": "https://kokkai.ndl.go.jp/txt/121104260X01020230421/115", "sentence": ["…交通省でより一元的に水道行政を担うことが効率的だと思います。わざわざ連携規定を設けなくてもよいと考えますので、前向きに御検討をいただきたいと…"]}]}]}, {"date": "2023-05-10", "meeting": [{"meeting_name": "衆議院 厚生労働委員会", "remarks": [{"url": "https://kokkai.ndl.go.jp/txt/121104260X01220230510/191", "sentence": []}, {"url": "https://kokkai.ndl.go.jp/txt/121104260X01220230510/193", "sentence": ["…して、厚生労働省、内閣官房、警察庁、文部科学省、総務省、法務省などが連携をして自殺対策に取り組むこととしています。四月二十七日には第一回こど…", "…が、自殺対策は厚労省が元来担ってきた部分でございますので、どのように連携をしていくのか、また、どのような対策を行っていくのか、御教示をくださ…"]}, {"url": "https://kokkai.ndl.go.jp/txt/121104260X01220230510/195", "sentence": ["…これまで行ってきた地域の実情に応じた自殺支援をこども家庭庁や他省庁と連携をしながら積極的に取り組んでいただき、困難を抱える子供たちが一日でも…"]}, {"url": "https://kokkai.ndl.go.jp/txt/121104260X01220230510/197", "sentence": []}, {"url": "https://kokkai.ndl.go.jp/txt/121104260X01220230510/199", "sentence": []}, {"url": "https://kokkai.ndl.go.jp/txt/121104260X01220230510/201", "sentence": []}, {"url": "https://kokkai.ndl.go.jp/txt/121104260X01220230510/203", "sentence": []}, {"url": "https://kokkai.ndl.go.jp/txt/121104260X01220230510/205", "sentence": []}, {"url": "https://kokkai.ndl.go.jp/txt/121104260X01220230510/207", "sentence": []}, {"url": "https://kokkai.ndl.go.jp/txt/121104260X01220230510/209", "sentence": []}, {"url": "https://kokkai.ndl.go.jp/txt/121104260X01220230510/211", "sentence": []}]}]}, {"date": "2023-05-25", "meeting": [{"meeting_name": "衆議院 災害対策特別委員会", "remarks": [{"url": "https://kokkai.ndl.go.jp/txt/121104339X00420230525/86", "sentence": []}, {"url": "https://kokkai.ndl.go.jp/txt/121104339X00420230525/88", "sentence": []}, {"url": "https://kokkai.ndl.go.jp/txt/121104339X00420230525/91", "sentence": ["…緊急地震速報が出たときに自動で最寄りの階に止まるエレベーターも、官民連携で普及させていく必要が国民の安心のためにはあるのではないかと考えます…"]}, {"url": "https://kokkai.ndl.go.jp/txt/121104339X00420230525/93", "sentence": ["…わけではなく、燃えない町をつくるためには、住民の意識の醸成と、国とも連携をした施策の後押しが必要と考えます。この火災について、別の観点からも…"]}, {"url": "https://kokkai.ndl.go.jp/txt/121104339X00420230525/96", "sentence": []}]}]}, {"date": "2024-02-29", "meeting": [{"meeting_name": "衆議院 総務委員会", "remarks": [{"url": "https://kokkai.ndl.go.jp/txt/121304601X00620240229/166", "sentence": []}, {"url": "https://kokkai.ndl.go.jp/txt/121304601X00620240229/168", "sentence": []}, {"url": "https://kokkai.ndl.go.jp/txt/121304601X00620240229/170", "sentence": []}, {"url": "https://kokkai.ndl.go.jp/txt/121304601X00620240229/172", "sentence": []}, {"url": "https://kokkai.ndl.go.jp/txt/121304601X00620240229/174", "sentence": []}, {"url": "https://kokkai.ndl.go.jp/txt/121304601X00620240229/176", "sentence": []}, {"url": "https://kokkai.ndl.go.jp/txt/121304601X00620240229/178", "sentence": []}, {"url": "https://kokkai.ndl.go.jp/txt/121304601X00620240229/180", "sentence": []}, {"url": "https://kokkai.ndl.go.jp/txt/121304601X00620240229/182", "sentence": []}, {"url": "https://kokkai.ndl.go.jp/txt/121304601X00620240229/184", "sentence": []}, {"url": "https://kokkai.ndl.go.jp/txt/121304601X00620240229/186", "sentence": ["…うな状況を踏まえて、令和六年度地方財政対策では、都道府県等が市町村と連携協約を締結の上、市町村が必要とする専門人材、例えば保育士や保健師、税…"]}, {"url": "https://kokkai.ndl.go.jp/txt/121304601X00620240229/188", "sentence": []}, {"url": "https://kokkai.ndl.go.jp/txt/121304601X00620240229/190", "sentence": []}]}]}, {"date": "2024-04-02", "meeting": [{"meeting_name": "衆議院 総務委員会", "remarks": [{"url": "https://kokkai.ndl.go.jp/txt/121304601X01120240402/163", "sentence": []}, {"url": "https://kokkai.ndl.go.jp/txt/121304601X01120240402/165", "sentence": []}, {"url": "https://kokkai.ndl.go.jp/txt/121304601X01120240402/167", "sentence": []}, {"url": "https://kokkai.ndl.go.jp/txt/121304601X01120240402/169", "sentence": ["…長期的な視点で整理した地域の未来予測を作成し、地域や組織の枠を超えた連携を長期的な視点で選択する必要があるとしています。現在の地域の未来予測…"]}, {"url": "https://kokkai.ndl.go.jp/txt/121304601X01120240402/171", "sentence": []}, {"url": "https://kokkai.ndl.go.jp/txt/121304601X01120240402/173", "sentence": ["…が、しかし、人口減少に伴い、今後、施設やインフラ整備、様々な点で広域連携が更に求められると考えます。よって、各市町村だけでこの未来予測を立て…", "…ではなく、県も一緒になって未来予測を立てる必要があると考えます。広域連携等での取組が必要だと考えますが、松本大臣の御見解をお聞かせください。"]}, {"url": "https://kokkai.ndl.go.jp/txt/121304601X01120240402/175", "sentence": ["…るかもしれませんけれども、作成することで、単独では難しい市町村が広域連携に踏み出すきっかけになるかと思います。続きまして、次の質問に移らせて…"]}, {"url": "https://kokkai.ndl.go.jp/txt/121304601X01120240402/177", "sentence": ["…しながら促進していただきたいと思います。この後、地域おこし協力隊との連携などを質問させていただく予定でございましたけれども、質問時間が終了と…"]}]}]}, {"date": "2024-04-09", "meeting": [{"meeting_name": "衆議院 本会議", "remarks": [{"url": "https://kokkai.ndl.go.jp/txt/121305254X01920240409/34", "sentence": []}]}, {"meeting_name": "衆議院 総務委員会", "remarks": [{"url": "https://kokkai.ndl.go.jp/txt/121304601X01320240409/81", "sentence": []}, {"url": "https://kokkai.ndl.go.jp/txt/121304601X01320240409/83", "sentence": []}, {"url": "https://kokkai.ndl.go.jp/txt/121304601X01320240409/85", "sentence": ["…方創生、地域活性化につながると考えますので、総務省と国交省がしっかり連携をしていただいて、横展開をしながら進めていただきたく、よろしくお願い…"]}, {"url": "https://kokkai.ndl.go.jp/txt/121304601X01320240409/87", "sentence": []}]}]}, {"date": "2024-04-25", "meeting": [{"meeting_name": "衆議院 総務委員会", "remarks": [{"url": "https://kokkai.ndl.go.jp/txt/121304601X01720240425/128", "sentence": []}, {"url": "https://kokkai.ndl.go.jp/txt/121304601X01720240425/131", "sentence": []}, {"url": "https://kokkai.ndl.go.jp/txt/121304601X01720240425/133", "sentence": []}, {"url": "https://kokkai.ndl.go.jp/txt/121304601X01720240425/135", "sentence": ["○吉田（と）委員民放との連携という観点では、既に地上デジタルテレビのＮＨＫの放送所約二千二百か所のうち約七割で民間放送事業者との共同建設が行…"]}, {"url": "https://kokkai.ndl.go.jp/txt/121304601X01720240425/137", "sentence": []}, {"url": "https://kokkai.ndl.go.jp/txt/121304601X01720240425/139", "sentence": []}, {"url": "https://kokkai.ndl.go.jp/txt/121304601X01720240425/141", "sentence": []}, {"url": "https://kokkai.ndl.go.jp/txt/121304601X01720240425/143", "sentence": []}]}]}, {"date": "2024-05-09", "meeting": [{"meeting_name": "衆議院 総務委員会", "remarks": [{"url": "https://kokkai.ndl.go.jp/txt/121304601X01820240509/66", "sentence": []}, {"url": "https://kokkai.ndl.go.jp/txt/121304601X01820240509/68", "sentence": []}, {"url": "https://kokkai.ndl.go.jp/txt/121304601X01820240509/70", "sentence": ["…したけれども、人の力による支援、そして双方を所管する総務省だからこそ連携した取組支援ができるんだと思います。松本大臣を筆頭に、総務省の皆様に…"]}]}]}]