[{"date": "2022-02-15", "meeting": [{"meeting_name": "衆議院 予算委員会公聴会", "remarks": [{"url": "https://kokkai.ndl.go.jp/txt/120805262X00120220215/142", "sentence": []}, {"url": "https://kokkai.ndl.go.jp/txt/120805262X00120220215/145", "sentence": []}, {"url": "https://kokkai.ndl.go.jp/txt/120805262X00120220215/147", "sentence": []}, {"url": "https://kokkai.ndl.go.jp/txt/120805262X00120220215/150", "sentence": ["…お話を伺ったんですが、お母さんからすると、もう介護することが息子が当たり前になり過ぎて、洗脳という言い方をされていたのが印象的でしたけれども…"]}, {"url": "https://kokkai.ndl.go.jp/txt/120805262X00120220215/152", "sentence": []}]}]}, {"date": "2022-04-07", "meeting": [{"meeting_name": "衆議院 総務委員会", "remarks": [{"url": "https://kokkai.ndl.go.jp/txt/120804601X01020220407/38", "sentence": ["…と思いますが、でも、女性に関しては大分、育児休業を取るという選択が当たり前になりつつあると思います。私自身も、女性が育休を取るんだと言ったら…", "…ってしまいそうになるということが、まだまだ、やはり男性の育休取得が当たり前になっていないのかなと思います。内閣府の「「第一子出産前後の女性の…"]}, {"url": "https://kokkai.ndl.go.jp/txt/120804601X01020220407/40", "sentence": []}, {"url": "https://kokkai.ndl.go.jp/txt/120804601X01020220407/42", "sentence": []}, {"url": "https://kokkai.ndl.go.jp/txt/120804601X01020220407/44", "sentence": []}, {"url": "https://kokkai.ndl.go.jp/txt/120804601X01020220407/46", "sentence": []}, {"url": "https://kokkai.ndl.go.jp/txt/120804601X01020220407/48", "sentence": []}, {"url": "https://kokkai.ndl.go.jp/txt/120804601X01020220407/50", "sentence": []}, {"url": "https://kokkai.ndl.go.jp/txt/120804601X01020220407/52", "sentence": []}, {"url": "https://kokkai.ndl.go.jp/txt/120804601X01020220407/54", "sentence": []}, {"url": "https://kokkai.ndl.go.jp/txt/120804601X01020220407/56", "sentence": []}, {"url": "https://kokkai.ndl.go.jp/txt/120804601X01020220407/58", "sentence": []}, {"url": "https://kokkai.ndl.go.jp/txt/120804601X01020220407/60", "sentence": []}, {"url": "https://kokkai.ndl.go.jp/txt/120804601X01020220407/62", "sentence": []}]}]}, {"date": "2023-02-16", "meeting": [{"meeting_name": "衆議院 総務委員会", "remarks": [{"url": "https://kokkai.ndl.go.jp/txt/121104601X00420230216/141", "sentence": []}, {"url": "https://kokkai.ndl.go.jp/txt/121104601X00420230216/143", "sentence": []}, {"url": "https://kokkai.ndl.go.jp/txt/121104601X00420230216/146", "sentence": []}, {"url": "https://kokkai.ndl.go.jp/txt/121104601X00420230216/148", "sentence": []}, {"url": "https://kokkai.ndl.go.jp/txt/121104601X00420230216/150", "sentence": []}, {"url": "https://kokkai.ndl.go.jp/txt/121104601X00420230216/152", "sentence": []}, {"url": "https://kokkai.ndl.go.jp/txt/121104601X00420230216/154", "sentence": []}, {"url": "https://kokkai.ndl.go.jp/txt/121104601X00420230216/156", "sentence": ["…るということが実際にあるそうでして、これは、隊員の方は人間ですので当たり前の話ですが、しっかり水分補給をされるとか休憩するとかトイレに行くと…", "…給をされるとか休憩するとかトイレに行くとか、こういう時間があるのは当たり前だと思わなきゃいけない。これは私たちの理解も当然必要だと思いますし…"]}, {"url": "https://kokkai.ndl.go.jp/txt/121104601X00420230216/158", "sentence": []}, {"url": "https://kokkai.ndl.go.jp/txt/121104601X00420230216/160", "sentence": []}, {"url": "https://kokkai.ndl.go.jp/txt/121104601X00420230216/162", "sentence": []}, {"url": "https://kokkai.ndl.go.jp/txt/121104601X00420230216/164", "sentence": []}, {"url": "https://kokkai.ndl.go.jp/txt/121104601X00420230216/166", "sentence": []}, {"url": "https://kokkai.ndl.go.jp/txt/121104601X00420230216/168", "sentence": []}]}]}, {"date": "2023-04-12", "meeting": [{"meeting_name": "衆議院 国土交通委員会", "remarks": [{"url": "https://kokkai.ndl.go.jp/txt/121104319X00920230412/54", "sentence": []}, {"url": "https://kokkai.ndl.go.jp/txt/121104319X00920230412/56", "sentence": ["…るという状況であるそうですけれども、やはり、こうした国のサポートが当たり前と思われないようにしなければならないということも重要だと私は感じて…"]}, {"url": "https://kokkai.ndl.go.jp/txt/121104319X00920230412/58", "sentence": []}, {"url": "https://kokkai.ndl.go.jp/txt/121104319X00920230412/60", "sentence": []}]}]}, {"date": "2023-04-13", "meeting": [{"meeting_name": "衆議院 総務委員会", "remarks": [{"url": "https://kokkai.ndl.go.jp/txt/121104601X01020230413/58", "sentence": []}, {"url": "https://kokkai.ndl.go.jp/txt/121104601X01020230413/60", "sentence": []}, {"url": "https://kokkai.ndl.go.jp/txt/121104601X01020230413/62", "sentence": []}, {"url": "https://kokkai.ndl.go.jp/txt/121104601X01020230413/64", "sentence": []}, {"url": "https://kokkai.ndl.go.jp/txt/121104601X01020230413/66", "sentence": []}, {"url": "https://kokkai.ndl.go.jp/txt/121104601X01020230413/68", "sentence": []}, {"url": "https://kokkai.ndl.go.jp/txt/121104601X01020230413/70", "sentence": []}, {"url": "https://kokkai.ndl.go.jp/txt/121104601X01020230413/72", "sentence": ["…立候補することができる、議員として活動することができるということを当たり前の流れにしていくのかどうなのかというのは今後のテーマになるかなと思…"]}, {"url": "https://kokkai.ndl.go.jp/txt/121104601X01020230413/74", "sentence": []}, {"url": "https://kokkai.ndl.go.jp/txt/121104601X01020230413/76", "sentence": []}, {"url": "https://kokkai.ndl.go.jp/txt/121104601X01020230413/78", "sentence": []}]}]}, {"date": "2023-06-16", "meeting": [{"meeting_name": "衆議院 本会議", "remarks": [{"url": "https://kokkai.ndl.go.jp/txt/121105254X03420230616/10", "sentence": ["…せん、難民の皆さんや、日本が当然守るべき命や人権を大切にすることが当たり前の国にするべきです。ＬＧＢＴなど性的マイノリティーは、性的指向、性…"]}]}]}]