[{"date": "2024-02-01", "meeting": [{"meeting_name": "参議院 本会議", "remarks": [{"url": "https://kokkai.ndl.go.jp/txt/121315254X00320240201/2", "sentence": ["…政務官と災害からの復旧復興を担当する国土交通大臣政務官が自民党の裏金事件を受けて突如辞任するとは、一体何をやっているのか。裏金を受け取りなが…", "…ました。最初の大きな改正は一九七五年、自民党を中心とした政界の黒い霧事件が起きて、金権政治に国民の不満が高まっていた時代です。その後、幾度も…", "…織的、積極的に行っていたことから、その悪質性はロッキードやリクルート事件を優に超えるのではないでしょうか。裏金議員は、明らかに議員辞職に値し…", "…党も除名も辞職もしない。これは一体どういうことでしょうか。ロッキード事件、リクルート事件の際には、国会は特別委員会を設置し、当事者たちを証人…", "…しない。これは一体どういうことでしょうか。ロッキード事件、リクルート事件の際には、国会は特別委員会を設置し、当事者たちを証人喚問して、究明と…", "…岸田総理は高らかに喧伝していますが、これは法改正も必要なほどの大きな事件です。総理に質問五です。自民党が本気であるのならば、政治刷新本部にお…"]}]}]}, {"date": "2024-06-19", "meeting": [{"meeting_name": "参議院 本会議", "remarks": [{"url": "https://kokkai.ndl.go.jp/txt/121315254X02820240619/28", "sentence": ["…の一部を改正する法律案に反対の立場で討論を行います。自民党派閥の裏金事件とそれに対する自民党の対応は、国民の政治に対する信頼を根本から損なう…", "…して初出席するなど、パフォーマンスばかりを繰り返しました。結局、裏金事件の真相は全く明らかになっておらず、その責任もあやふやなままで、信頼回…", "…の改正案では裏金の温床とも言える政策活動費が温存される点です。今回の事件では、派閥からの裏金を政策活動費と認識していたとの説明がなされました…", "…められたことから、政党支部経由の献金がまかり通るとともに、今回、裏金事件の舞台となった政治資金パーティーが企業・団体献金の代わりとして活用さ…", "…治を実現するものではありません。こんな抜け道だらけの規正法改正で裏金事件の幕引きとは、自民党は国民の怒りを甘く見過ぎてはいないですか。幕を引…", "…自民党は国民の怒りを甘く見過ぎてはいないですか。幕を引くべきは、裏金事件だけではなく、自民党政治そのものです。国民の期待に応え、本気の政治改…"]}]}]}]